slimish_jinja/__init__.py
slimish_jinja/lexer.py
slimish_jinja/parse.py
slimish_jinja/slimish_jinja.py
slimish_jinja/tokens.py
slimish_jinja-1.1.2.data/scripts/slim_to_jinja.py
slimish_jinja-1.1.2.dist-info/LICENSE
slimish_jinja-1.1.2.dist-info/METADATA
slimish_jinja-1.1.2.dist-info/WHEEL
slimish_jinja-1.1.2.dist-info/top_level.txt
slimish_jinja-1.1.2.dist-info/RECORD
