Metadata-Version: 2.1
Name: slimish-jinja
Version: 1.1.2
Summary: Slim templates syntax for Jinja2 templates
Home-page: https://github.com/thoughtnirvana/slimish-jinja2
Author: Rahul Kumar
Author-email: rahul@thoughtnirvana.com
License: BSD
Platform: UNKNOWN
Classifier: Programming Language :: Python :: 3
Classifier: License :: OSI Approved :: BSD License
Classifier: Operating System :: OS Independent
Requires-Dist: future
Requires-Dist: jinja2
